<?xml version="1.0" encoding="UTF-8"?>
<schemalist >
    <schema id="com.unikylin.kiran.touchpad" path="/com/unikylin/kiran/touchpad/">
        <key name="left-handed" type="b">
            <default>false</default>
            <summary>Swap left and right mouse buttons for left-handed mice.</summary>
        </key>

        <key name="disable-while-typing" type="b">
            <default>true</default>
            <summary>Indicates if diable while typing is enabled or disabled.</summary>
        </key>

        <key name="tap-to-click" type="b">
            <default>true</default>
            <summary>Set this to TRUE to be able to send mouse clicks by tapping on the touchpad.</summary>
        </key>

        <key name="click-method" type="i">
            <default>0</default>
            <range min="0" max="1" />
            <summary>Enables a click method. Permitted methods are buttonareas and clickfinger, respectively conreesponding to 0 and 1.</summary>
        </key>

        <key name="scroll-method" type="i">
            <default>0</default>
            <range min="0" max="2" />
            <summary>Enables a scroll method. Permitted methods are twofinger, edge and button, respectively conrresponding to 0, 1 and 2.</summary>
        </key>

        <key name="natural-scroll" type="b">
            <default>false</default>
            <summary>Enables or disables natural scroll. "Natural scrolling”is the terminology for moving the content in the direction of scrolling, 
            i.e. moving the wheel or fingers down moves the page down.</summary>
        </key>

        <key name="touchpad-enabled" type="b">
            <default>true</default>
            <summary>Set this to TRUE to enable all touchpads.</summary>
        </key>

        <key name="motion-acceleration" type="d">
            <default>5.5</default>
            <range min="1" max="10" />
            <summary>Acceleration multiplier for mouse motion.</summary>
        </key>
    </schema>
</schemalist>
